seele_app/__init__.py
seele_app/entrypoint.py
seele_app/settings.py
seele_app/urls.py
seele_app/urls_i18n.py
seele_app/wsgi.py
seele_app/__pycache__/__init__.cpython-310.pyc
seele_app/__pycache__/__init__.cpython-312.pyc
seele_app/__pycache__/settings.cpython-310.pyc
seele_app/__pycache__/settings.cpython-312.pyc
seele_app/__pycache__/urls.cpython-310.pyc
seele_app/__pycache__/urls.cpython-312.pyc
seele_app/__pycache__/urls_i18n.cpython-310.pyc
seele_app/__pycache__/urls_i18n.cpython-312.pyc
seele_app/__pycache__/utils.cpython-310.pyc
seele_app/__pycache__/views.cpython-310.pyc
seele_app/__pycache__/wsgi.cpython-310.pyc
seele_app/__pycache__/wsgi.cpython-312.pyc
seele_app/locale/jp/LC_MESSAGES/django.mo
seele_app/locale/jp/LC_MESSAGES/django.po
website/__init__.py
website/admin.py
website/apps.py
website/models.py
website/tests.py
website/utils.py
website/views.py
website/__pycache__/__init__.cpython-310.pyc
website/__pycache__/__init__.cpython-312.pyc
website/__pycache__/admin.cpython-310.pyc
website/__pycache__/admin.cpython-312.pyc
website/__pycache__/apps.cpython-310.pyc
website/__pycache__/apps.cpython-312.pyc
website/__pycache__/models.cpython-310.pyc
website/__pycache__/models.cpython-312.pyc
website/__pycache__/utils.cpython-310.pyc
website/__pycache__/utils.cpython-312.pyc
website/__pycache__/views.cpython-310.pyc
website/__pycache__/views.cpython-312.pyc
website/migrations/0001_initial.py
website/migrations/0002_remove_users_mobile.py
website/migrations/0003_users_location.py
website/migrations/0004_users_family_size.py
website/migrations/0005_alter_users_family_size.py
website/migrations/0006_users_medical_issues_users_medication_amount.py
website/migrations/0007_users_baby_bool_users_child_bool_users_women_bool.py
website/migrations/0008_users_latitude_users_longitude_alter_users_location.py
website/migrations/__init__.py
website/migrations/__pycache__/0001_initial.cpython-310.pyc
website/migrations/__pycache__/0001_initial.cpython-312.pyc
seele_web-0.0.5.dist-info/LICENSE
seele_web-0.0.5.dist-info/METADATA
seele_web-0.0.5.dist-info/WHEEL
seele_web-0.0.5.dist-info/entry_points.txt
seele_web-0.0.5.dist-info/top_level.txt
seele_web-0.0.5.dist-info/RECORD
